pytest_smtp_test_server/__init__.py
pytest_smtp_test_server/exceptions.py
pytest_smtp_test_server/fixture.py
pytest_smtp_test_server/init.py
pytest_smtp_test_server/internal.py
pytest_smtp_test_server/plugin.py
pytest_smtp_test_server/version_check.py
pytest_smtp_test_server-0.1.1.dist-info/LICENSE.txt
pytest_smtp_test_server-0.1.1.dist-info/METADATA
pytest_smtp_test_server-0.1.1.dist-info/WHEEL
pytest_smtp_test_server-0.1.1.dist-info/entry_points.txt
pytest_smtp_test_server-0.1.1.dist-info/RECORD
