Metadata-Version: 2.1
Name: pytest-smtp-test-server
Version: 0.1.1
Summary: pytest plugin for using `smtp-test-server` as a fixture
Home-page: https://git.codebau.dev/pytest-plugins/pytest-smtp-test-server
License: MIT
Keywords: py.test,pytest,pytest-plugin,mail,smtp,mock,fixture
Author: Juergen Edelbluth
Author-email: pytest-smtp-test-server@jued.de
Requires-Python: >=3.11,<4.0
Classifier: Development Status :: 2 - Pre-Alpha
Classifier: Environment :: Console
Classifier: Environment :: Plugins
Classifier: Framework :: Pytest
Classifier: Intended Audience :: Developers
Classifier: License :: OSI Approved :: MIT License
Classifier: Operating System :: MacOS :: MacOS X
Classifier: Operating System :: Microsoft :: Windows
Classifier: Operating System :: POSIX
Classifier: Programming Language :: Python :: 3
Classifier: Programming Language :: Python :: 3.11
Classifier: Programming Language :: Python :: 3.12
Classifier: Topic :: Software Development :: Quality Assurance
Classifier: Topic :: Software Development :: Testing
Classifier: Topic :: Utilities
Requires-Dist: pytest (>=7.4.3,<8.0.0)
Requires-Dist: smtp-test-server (>=0.1.0,<0.2.0)
Project-URL: Changelog, https://git.codebau.dev/pytest-plugins/pytest-smtp-test-server/CHANGELOG.md
Project-URL: Documentation, https://git.codebau.dev/pytest-plugins/pytest-smtp-test-server/
Project-URL: Issue Tracker, https://git.codebau.dev/pytest-plugins/pytest-smtp-test-server/issues
Project-URL: Repository, https://git.codebau.dev/pytest-plugins/pytest-smtp-test-server
Project-URL: Releases, https://git.codebau.dev/pytest-plugins/pytest-smtp-test-server/releases
Project-URL: Wiki, https://git.codebau.dev/pytest-plugins/pytest-smtp-test-server/wiki
